examples/__init__.py
examples/example.py
flask_curd_db/__init__.py
flask_curd_db/db.py
Flask_Curd_Db-1.0.0.dist-info/LICENSE.txt
Flask_Curd_Db-1.0.0.dist-info/METADATA
Flask_Curd_Db-1.0.0.dist-info/WHEEL
Flask_Curd_Db-1.0.0.dist-info/top_level.txt
Flask_Curd_Db-1.0.0.dist-info/RECORD
