Metadata-Version: 2.1
Name: Flask-Curd-Db
Version: 1.0.0
Summary: flask curd db method
Home-page: https://github.com/libaibuaidufu/Flask-Curd-Db.git
Author: libaibuaidufu
Author-email: libaibuaidufu@gmail.com
License: MIT License
Keywords: flask curd db method
Platform: any
Requires-Dist: sqlalchemy
